tests/__init__.py
tests/_utils.py
tests/common/__init__.py
tests/common/test_ModelBuilder.py
tests/common/test_NodeBuilder.py
tests/common/test_Opset.py
tests/common/test_quantize.py
tests/common/test_utils.py
tests/common/test_version.py
tests/coreml/__init__.py
tests/coreml/test_coreml.py
tests/keras/__init__.py
tests/keras/test_keras.py
tests/lightgbm/__init__.py
tests/lightgbm/test_lightgbm.py
tests/sklearn/__init__.py
tests/sklearn/test_sklearn.py
tests/sparkml/__init__.py
tests/sparkml/sparkml_test_base.py
tests/sparkml/sparkml_test_utils.py
tests/sparkml/test_logistic_regression.py
tests/svmlib/__init__.py
tests/svmlib/test_SVMConverters.py
tests/tensorflow/__init__.py
tests/tensorflow/test_tensorflow.py
tests/xgboost/__init__.py
tests/xgboost/test_XGBoostConverters.py
winmltools/__init__.py
winmltools/config.py
winmltools/convert/__init__.py
winmltools/convert/main.py
winmltools/convert/common/ConvertContext.py
winmltools/convert/common/ModelBuilder.py
winmltools/convert/common/Node.py
winmltools/convert/common/NodeBuilder.py
winmltools/convert/common/__init__.py
winmltools/convert/common/_utils.py
winmltools/convert/common/data_types.py
winmltools/convert/common/model_util.py
winmltools/convert/common/registration.py
winmltools/proto/__init__.py
winmltools/utils/__init__.py
winmltools/utils/quantize.py
winmltools-1.5.1.dist-info/LICENSE
winmltools-1.5.1.dist-info/METADATA
winmltools-1.5.1.dist-info/WHEEL
winmltools-1.5.1.dist-info/top_level.txt
winmltools-1.5.1.dist-info/RECORD
