Metadata-Version: 2.1
Name: winmltools
Version: 1.5.1
Summary: Converts Machine Learning models to ONNX for use in Windows ML
Home-page: https://microsoft.com
Author: Microsoft Corporation
Author-email: winml@microsoft.com
License: MIT License
Platform: UNKNOWN
Classifier: Development Status :: 5 - Production/Stable
Classifier: Environment :: Console
Classifier: Intended Audience :: Developers
Classifier: Operating System :: MacOS :: MacOS X
Classifier: Operating System :: Microsoft :: Windows
Classifier: Programming Language :: Python
Classifier: Programming Language :: Python :: 2.7
Classifier: Programming Language :: Python :: 3.5
Classifier: Programming Language :: Python :: 3.6
Classifier: License :: OSI Approved :: MIT License
Requires-Dist: numpy (==1.16.4)
Requires-Dist: protobuf (==3.6.1)
Requires-Dist: onnx (==1.5.0)
Requires-Dist: onnxmltools (==1.5.1)
Requires-Dist: tf2onnx (==1.5.3)
